LICENSE.txt
MANIFEST.in
README.rst
release-history.rst
requirements.txt
setup.py
constant/__init__.py
constant/base.py
constant/const.py
constant/exc.py
constant/zzz_manual_install.py
constant.egg-info/PKG-INFO
constant.egg-info/SOURCES.txt
constant.egg-info/dependency_links.txt
constant.egg-info/requires.txt
constant.egg-info/top_level.txt
constant/__pycache__/__init__.cpython-34.pyc
constant/__pycache__/base.cpython-34.pyc
constant/__pycache__/const.cpython-34.pyc
constant/__pycache__/exc.cpython-34.pyc
constant/pkg/__init__.py
constant/pkg/class_metadata.py
constant/pkg/name_convention.py
constant/pkg/nameddict.py
constant/pkg/pylru.py
constant/pkg/sixmini.py
constant/pkg/__pycache__/__init__.cpython-34.pyc
constant/pkg/__pycache__/name_convention.cpython-34.pyc
constant/pkg/__pycache__/nameddict.cpython-34.pyc
constant/pkg/__pycache__/pylru.cpython-34.pyc
constant/pkg/__pycache__/sixmini.cpython-34.pyc
constant/test/__init__.py
constant/test/creature.py
constant/test/creature_data.py
constant/test/food.py
constant/test/food_data.py
constant/test/inventory.py
constant/test/inventory_data.py
constant/test/item.py
constant/test/item_data.py
constant/test/validate_implementation.py
constant/test/__pycache__/__init__.cpython-34.pyc
constant/test/__pycache__/food.cpython-34.pyc
constant/test/dev/__init__.py
constant/test/dev/food_data_example.py
constant/test/dev/food_example.py
constant/tpl/__init__.py
constant/tpl/class_def.py
constant/tpl/env.py
constant/tpl/__pycache__/__init__.cpython-34.pyc
constant/tpl/__pycache__/class_def.cpython-34.pyc
constant/tpl/__pycache__/env.cpython-34.pyc
constant/tpl/templates/class_def.txt
constant/tpl/templates/code.txt
constant/tpl/templates/collection_class_def.txt